{"type": "Feature", "id": 12517669, "properties": {"woe:id": 12517669, "woe:parent_id": 887115, "woe:name": "Pite\u00e5 Flygplats", "woe:placetype": 14, "woe:placetype_name": "Airport", "woe:lang": "SWE", "iso:country": "SE", "meta:provider": ["geoplanet:7.3.1", "geoplanet:7.3.2", "geoplanet:7.4.0", "geoplanet:7.4.1", "geoplanet:7.5.1", "geoplanet:7.5.2", "geoplanet:7.6.0", "geoplanet:7.8.1", "geoplanet:7.9.0", "geoplanet:7.10.0", "geoplanet:8.0.0", "woeplanet:8.0.0"], "meta:indexed": "2020-08-20T21:02:32.167123", "meta:updated": "2020-08-22T01:57:23.180302", "woe:alias_ENG_P": ["Pitea Airport"], "woe:alias_SWE_S": ["Pitea Flygplats"], "woe:hierarchy": {"continent": 24865675, "country": 23424954, "town": 0, "planet": 1, "county": 12587355, "suburb": 0, "state": 2347057, "region": 0, "localadmin": 0}, "woe:timezone_id": 28350917, "woe:hash": "u7xh5csgj7td", "woe:centroid": [21.265301, 65.399399], "geom:latitude": 65.399399, "geom:longitude": 21.265301, "geom:hash": "u7xh5csgj7td", "woe:latitude": 65.399399, "geom:centroid": [21.265301, 65.399399], "woe:longitude": 21.265301, "woe:repo": "woeplanet-airport-se"}, "geometry": {"coordinates": [21.265301, 65.399399], "type": "Point"}}