{"type": "Feature", "id": 12517660, "geometry": {"type": "Point", "coordinates": [18.70743, 64.550392]}, "properties": {"woe:id": 12517660, "woe:parent_id": 897946, "woe:name": "Lycksele Flygplats", "woe:placetype": 14, "woe:placetype_name": "Airport", "woe:lang": "SWE", "iso:country": "SE", "meta:provider": ["geoplanet:7.3.1", "geoplanet:7.3.2", "geoplanet:7.4.0", "geoplanet:7.4.1", "geoplanet:7.5.1", "geoplanet:7.5.2", "geoplanet:7.6.0", "geoplanet:7.8.1", "geoplanet:7.9.0", "geoplanet:7.10.0", "geoplanet:8.0.0", "woeplanet:8.0.0"], "meta:indexed": "2020-08-20T21:02:32.163192", "woe:alias_DAN_Q": ["Lycksele Lufthavn"], "woe:alias_ENG_V": ["LYC", "LYC Airport"], "woe:alias_FRE_Q": ["A\u00e9roport de Lycksele"], "woe:alias_CZE_Q": ["Letiste Lycksele"], "woe:alias_FIN_Q": ["Lyckselen Lentoasema"], "woe:alias_ENG_P": ["Lycksele Airport"], "woe:alias_UNK_Q": ["Letisko Lycksele"], "woe:alias_DUT_Q": ["Luchthaven Lycksele"], "woe:alias_GER_Q": ["Flughafen Lycksele"], "woe:alias_SWE_V": ["LYC Flygplats"], "meta:updated": "2020-10-14T11:12:06.356457", "woe:alias_ITA_Q": ["Aeroporto di Lycksele"], "woe:alias_SPA_Q": ["Aeropuerto de Lycksele"], "woe:alias_FRE_S": ["Aeroport de Lycksele"], "woe:alias_POR_Q": ["Aeroporto de Lycksele"], "woe:hierarchy": {"continent": 24865675, "country": 23424954, "town": 0, "planet": 1, "county": 12587432, "suburb": 0, "state": 2347064, "region": 0, "localadmin": 0}, "woe:timezone_id": 28350917, "woe:hash": "u7mr1xn369ny", "woe:centroid": [18.70743, 64.550392], "geom:latitude": 64.550392, "geom:longitude": 18.70743, "geom:hash": "u7mr1xn369ny", "woe:latitude": 64.550392, "geom:centroid": [18.70743, 64.550392], "woe:longitude": 18.70743, "woe:repo": "woeplanet-airport-se", "geom:area": 0.0, "woe:scale": 19}}