{"type": "Feature", "id": 22656499, "properties": {"woe:id": 22656499, "woe:parent_id": 894059, "woe:name": "Idre Flygplats", "woe:placetype": 14, "woe:placetype_name": "Airport", "woe:lang": "SWE", "iso:country": "SE", "meta:provider": ["geoplanet:7.3.1", "geoplanet:7.3.2", "geoplanet:7.4.0", "geoplanet:7.4.1", "geoplanet:7.5.1", "geoplanet:7.5.2", "geoplanet:7.6.0", "geoplanet:7.8.1", "geoplanet:7.9.0", "geoplanet:7.10.0", "geoplanet:8.0.0", "woeplanet:8.0.0"], "meta:indexed": "2020-08-20T21:02:32.179384", "meta:updated": "2020-08-22T01:57:23.187593", "woe:alias_ENG_P": ["Idre Airport"], "woe:hierarchy": {"continent": 24865675, "country": 23424954, "town": 0, "planet": 1, "county": 12587286, "suburb": 0, "state": 2347053, "region": 0, "localadmin": 0}, "woe:timezone_id": 28350917, "woe:hash": "u6cpbxnbqpxw", "woe:centroid": [12.68776, 61.869591], "geom:latitude": 61.869591, "geom:longitude": 12.68776, "geom:hash": "u6cpbxnbqpxw", "woe:latitude": 61.869591, "geom:centroid": [12.68776, 61.869591], "woe:longitude": 12.68776, "woe:repo": "woeplanet-airport-se"}, "geometry": {"coordinates": [12.68776, 61.869591], "type": "Point"}}