{"type": "Feature", "id": 12517614, "properties": {"woe:id": 12517614, "woe:parent_id": 902695, "woe:name": "D\u00e5la Flygplats", "woe:placetype": 14, "woe:placetype_name": "Airport", "woe:lang": "SWE", "iso:country": "SE", "meta:provider": ["geoplanet:7.3.1", "geoplanet:7.3.2", "geoplanet:7.4.0", "geoplanet:7.4.1", "geoplanet:7.5.1", "geoplanet:7.5.2", "geoplanet:7.6.0", "geoplanet:7.8.1", "geoplanet:7.9.0", "geoplanet:7.10.0", "geoplanet:8.0.0", "woeplanet:8.0.0"], "meta:indexed": "2020-08-20T21:02:32.181285", "woe:alias_ENG_V": ["Borlange Airport", "BLE", "BLE Airport"], "woe:alias_FRE_Q": ["A\u00e9roport de Dala"], "woe:alias_CZE_Q": ["Letiste Dala"], "woe:alias_FIN_Q": ["Dalan Lentoasema"], "woe:alias_ENG_P": ["Dala Airport"], "woe:alias_UNK_Q": ["Letisko Dala"], "woe:alias_DUT_Q": ["Luchthaven Dala"], "woe:alias_GER_Q": ["Flughafen Dala"], "woe:alias_SWE_V": ["BLE Flygplats", "Borl\u00e4nge Flygplats"], "meta:updated": "2020-08-22T01:57:23.189407", "woe:alias_ITA_Q": ["Aeroporto di Dala"], "woe:alias_SPA_Q": ["Aeropuerto de Dala"], "woe:alias_FRE_S": ["Aeroport de Dala"], "woe:alias_SWE_S": ["Daala Flygplats", "Borlange Flygplats", "Dala Flygplats", "Borlaenge Flygplats"], "woe:alias_POR_Q": ["Aeroporto de Dala"], "woe:hierarchy": {"continent": 24865675, "country": 23424954, "town": 0, "planet": 1, "county": 12587288, "suburb": 0, "state": 2347053, "region": 0, "localadmin": 0}, "woe:timezone_id": 28350917, "woe:hash": "u6epbbut7d8s", "woe:centroid": [15.50804, 60.42984], "geom:latitude": 60.42984, "geom:longitude": 15.50804, "geom:hash": "u6epbbut7d8s", "woe:latitude": 60.42984, "geom:centroid": [15.50804, 60.42984], "woe:longitude": 15.50804, "woe:repo": "woeplanet-airport-se"}, "geometry": {"coordinates": [15.50804, 60.42984], "type": "Point"}}