{"type": "Feature", "id": 12517617, "geometry": {"type": "Point", "coordinates": [13.6042, 56.7836]}, "properties": {"woe:id": 12517617, "woe:parent_id": 891202, "woe:name": "Byholma Flygplats", "woe:placetype": 14, "woe:placetype_name": "Airport", "woe:lang": "SWE", "iso:country": "SE", "meta:provider": ["geoplanet:7.3.1", "geoplanet:7.3.2", "geoplanet:7.4.0", "geoplanet:7.4.1", "geoplanet:7.5.1", "geoplanet:7.5.2", "geoplanet:7.6.0", "geoplanet:7.8.1", "geoplanet:7.9.0", "geoplanet:7.10.0", "geoplanet:8.0.0", "woeplanet:8.0.0"], "meta:indexed": "2020-08-20T21:02:32.145611", "meta:updated": "2020-10-14T11:12:06.316701", "woe:alias_ENG_P": ["Byholma Airport"], "woe:hierarchy": {"continent": 24865675, "country": 23424954, "town": 0, "planet": 1, "county": 12587317, "suburb": 0, "state": 2347055, "region": 0, "localadmin": 0}, "woe:timezone_id": 28350917, "woe:hash": "u61ej94k2y4z", "woe:centroid": [13.6042, 56.7836], "geom:latitude": 56.7836, "geom:longitude": 13.6042, "geom:hash": "u61ej94k2y4z", "woe:latitude": 56.7836, "geom:centroid": [13.6042, 56.7836], "woe:longitude": 13.6042, "woe:repo": "woeplanet-airport-se", "geom:area": 0.0, "woe:scale": 19}}